setup.py
cim/__init__.py
cim/cim.py
cim/common.py
cim/formatters.py
cim/mutablenamedtuple.py
cim/objects.py
python_cim.egg-info/PKG-INFO
python_cim.egg-info/SOURCES.txt
python_cim.egg-info/dependency_links.txt
python_cim.egg-info/requires.txt
python_cim.egg-info/top_level.txt