Metadata-Version: 1.0
Name: python-cim
Version: 1.1
Summary: Pure Python parser for Windows WMI CIM respository databases.
Home-page: https://github.com/williballenthin/python-cim
Author: Willi Ballenthin
Author-email: william.ballenthin@fireeye.com
License: Apache 2.0 License
Platform: UNKNOWN
